{
  "openapi": "3.0.1",
  "info": {
    "title": "MultiShop.Order.WebApi",
    "version": "1.0"
  },
  "paths": {
    "/api/Addresses": {
      "get": {
        "tags": [
          "Addresses"
        ],
        "responses": {
          "200": {
            "description": "Success"
          }
        }
      },
      "post": {
        "tags": [
          "Addresses"
        ],
        "requestBody": {
          "content": {
            "application/json": {
              "schema": {
                "$ref": "#/components/schemas/CreateAddressCommand"
              }
            },
            "text/json": {
              "schema": {
                "$ref": "#/components/schemas/CreateAddressCommand"
              }
            },
            "application/*+json": {
              "schema": {
                "$ref": "#/components/schemas/CreateAddressCommand"
              }
            }
          }
        },
        "responses": {
          "200": {
            "description": "Success"
          }
        }
      },
      "put": {
        "tags": [
          "Addresses"
        ],
        "requestBody": {
          "content": {
            "application/json": {
              "schema": {
                "$ref": "#/components/schemas/UpdateAddressCommand"
              }
            },
            "text/json": {
              "schema": {
                "$ref": "#/components/schemas/UpdateAddressCommand"
              }
            },
            "application/*+json": {
              "schema": {
                "$ref": "#/components/schemas/UpdateAddressCommand"
              }
            }
          }
        },
        "responses": {
          "200": {
            "description": "Success"
          }
        }
      },
      "delete": {
        "tags": [
          "Addresses"
        ],
        "parameters": [
          {
            "name": "id",
            "in": "query",
            "schema": {
              "type": "integer",
              "format": "int32"
            }
          }
        ],
        "responses": {
          "200": {
            "description": "Success"
          }
        }
      }
    },
    "/api/Addresses/{id}": {
      "get": {
        "tags": [
          "Addresses"
        ],
        "parameters": [
          {
            "name": "id",
            "in": "path",
            "required": true,
            "schema": {
              "type": "integer",
              "format": "int32"
            }
          }
        ],
        "responses": {
          "200": {
            "description": "Success"
          }
        }
      }
    },
    "/api/OrderDetails": {
      "get": {
        "tags": [
          "OrderDetails"
        ],
        "responses": {
          "200": {
            "description": "Success"
          }
        }
      },
      "post": {
        "tags": [
          "OrderDetails"
        ],
        "requestBody": {
          "content": {
            "application/json": {
              "schema": {
                "$ref": "#/components/schemas/CreateOrderDetailCommand"
              }
            },
            "text/json": {
              "schema": {
                "$ref": "#/components/schemas/CreateOrderDetailCommand"
              }
            },
            "application/*+json": {
              "schema": {
                "$ref": "#/components/schemas/CreateOrderDetailCommand"
              }
            }
          }
        },
        "responses": {
          "200": {
            "description": "Success"
          }
        }
      },
      "delete": {
        "tags": [
          "OrderDetails"
        ],
        "parameters": [
          {
            "name": "id",
            "in": "query",
            "schema": {
              "type": "integer",
              "format": "int32"
            }
          }
        ],
        "responses": {
          "200": {
            "description": "Success"
          }
        }
      },
      "put": {
        "tags": [
          "OrderDetails"
        ],
        "requestBody": {
          "content": {
            "application/json": {
              "schema": {
                "$ref": "#/components/schemas/UpdateOrderDetailCommand"
              }
            },
            "text/json": {
              "schema": {
                "$ref": "#/components/schemas/UpdateOrderDetailCommand"
              }
            },
            "application/*+json": {
              "schema": {
                "$ref": "#/components/schemas/UpdateOrderDetailCommand"
              }
            }
          }
        },
        "responses": {
          "200": {
            "description": "Success"
          }
        }
      }
    },
    "/api/OrderDetails/{id}": {
      "get": {
        "tags": [
          "OrderDetails"
        ],
        "parameters": [
          {
            "name": "id",
            "in": "path",
            "required": true,
            "schema": {
              "type": "integer",
              "format": "int32"
            }
          }
        ],
        "responses": {
          "200": {
            "description": "Success"
          }
        }
      }
    },
    "/api/Orderings": {
      "get": {
        "tags": [
          "Orderings"
        ],
        "responses": {
          "200": {
            "description": "Success"
          }
        }
      },
      "post": {
        "tags": [
          "Orderings"
        ],
        "requestBody": {
          "content": {
            "application/json": {
              "schema": {
                "$ref": "#/components/schemas/CreateOrderingCommand"
              }
            },
            "text/json": {
              "schema": {
                "$ref": "#/components/schemas/CreateOrderingCommand"
              }
            },
            "application/*+json": {
              "schema": {
                "$ref": "#/components/schemas/CreateOrderingCommand"
              }
            }
          }
        },
        "responses": {
          "200": {
            "description": "Success"
          }
        }
      },
      "delete": {
        "tags": [
          "Orderings"
        ],
        "parameters": [
          {
            "name": "id",
            "in": "query",
            "schema": {
              "type": "integer",
              "format": "int32"
            }
          }
        ],
        "responses": {
          "200": {
            "description": "Success"
          }
        }
      },
      "put": {
        "tags": [
          "Orderings"
        ],
        "requestBody": {
          "content": {
            "application/json": {
              "schema": {
                "$ref": "#/components/schemas/UpdateOrderingCommand"
              }
            },
            "text/json": {
              "schema": {
                "$ref": "#/components/schemas/UpdateOrderingCommand"
              }
            },
            "application/*+json": {
              "schema": {
                "$ref": "#/components/schemas/UpdateOrderingCommand"
              }
            }
          }
        },
        "responses": {
          "200": {
            "description": "Success"
          }
        }
      }
    },
    "/api/Orderings/{id}": {
      "get": {
        "tags": [
          "Orderings"
        ],
        "parameters": [
          {
            "name": "id",
            "in": "path",
            "required": true,
            "schema": {
              "type": "integer",
              "format": "int32"
            }
          }
        ],
        "responses": {
          "200": {
            "description": "Success"
          }
        }
      }
    },
    "/api/Orderings/GetOrderingByUserId/{id}": {
      "get": {
        "tags": [
          "Orderings"
        ],
        "parameters": [
          {
            "name": "id",
            "in": "path",
            "required": true,
            "schema": {
              "type": "string"
            }
          }
        ],
        "responses": {
          "200": {
            "description": "Success"
          }
        }
      }
    }
  },
  "components": {
    "schemas": {
      "CreateAddressCommand": {
        "type": "object",
        "properties": {
          "addressId": {
            "type": "integer",
            "format": "int32"
          },
          "userId": {
            "type": "string",
            "nullable": true
          },
          "district": {
            "type": "string",
            "nullable": true
          },
          "city": {
            "type": "string",
            "nullable": true
          },
          "detail1": {
            "type": "string",
            "nullable": true
          }
        },
        "additionalProperties": false
      },
      "CreateOrderDetailCommand": {
        "type": "object",
        "properties": {
          "productId": {
            "type": "string",
            "nullable": true
          },
          "productName": {
            "type": "string",
            "nullable": true
          },
          "productPrice": {
            "type": "number",
            "format": "double"
          },
          "productAmount": {
            "type": "integer",
            "format": "int32"
          },
          "productTotalPrice": {
            "type": "number",
            "format": "double"
          },
          "orderingId": {
            "type": "integer",
            "format": "int32"
          }
        },
        "additionalProperties": false
      },
      "CreateOrderingCommand": {
        "type": "object",
        "properties": {
          "userId": {
            "type": "string",
            "nullable": true
          },
          "totalPrice": {
            "type": "number",
            "format": "double"
          },
          "orderDate": {
            "type": "string",
            "format": "date-time"
          }
        },
        "additionalProperties": false
      },
      "UpdateAddressCommand": {
        "type": "object",
        "properties": {
          "addressId": {
            "type": "integer",
            "format": "int32"
          },
          "userId": {
            "type": "string",
            "nullable": true
          },
          "district": {
            "type": "string",
            "nullable": true
          },
          "city": {
            "type": "string",
            "nullable": true
          },
          "detail": {
            "type": "string",
            "nullable": true
          }
        },
        "additionalProperties": false
      },
      "UpdateOrderDetailCommand": {
        "type": "object",
        "properties": {
          "orderDetailId": {
            "type": "integer",
            "format": "int32"
          },
          "productId": {
            "type": "string",
            "nullable": true
          },
          "productName": {
            "type": "string",
            "nullable": true
          },
          "productPrice": {
            "type": "number",
            "format": "double"
          },
          "productAmount": {
            "type": "integer",
            "format": "int32"
          },
          "productTotalPrice": {
            "type": "number",
            "format": "double"
          },
          "orderingId": {
            "type": "integer",
            "format": "int32"
          }
        },
        "additionalProperties": false
      },
      "UpdateOrderingCommand": {
        "type": "object",
        "properties": {
          "orderingId": {
            "type": "integer",
            "format": "int32"
          },
          "userId": {
            "type": "string",
            "nullable": true
          },
          "totalPrice": {
            "type": "number",
            "format": "double"
          },
          "orderDate": {
            "type": "string",
            "format": "date-time"
          }
        },
        "additionalProperties": false
      }
    }
  }
}